mswordtree/Helper.py
mswordtree/Item.py
mswordtree/__init__.py
mswordtree/app.py
mswordtree/mswordtree.py
mswordtree-0.1.1.7.dist-info/LICENSE
mswordtree-0.1.1.7.dist-info/METADATA
mswordtree-0.1.1.7.dist-info/WHEEL
mswordtree-0.1.1.7.dist-info/top_level.txt
mswordtree-0.1.1.7.dist-info/RECORD
