Metadata-Version: 2.1
Name: mswordtree
Version: 0.1.1.7
Summary: Get the parsed microsoft word document in a hierarchical tree structure.
Home-page: https://github.com/imAliAsad/mswordtree
Author: Ali Asad
Author-email: imaliasad@outlook.com
License: MIT License
Keywords: docx office openxml word tree microsoft headings tables
Platform: UNKNOWN
Classifier: Development Status :: 3 - Alpha
Classifier: Environment :: Console
Classifier: Intended Audience :: Developers
Classifier: License :: OSI Approved :: MIT License
Classifier: Operating System :: OS Independent
Classifier: Programming Language :: Python
Classifier: Programming Language :: Python :: 2
Classifier: Programming Language :: Python :: 2.6
Classifier: Programming Language :: Python :: 2.7
Classifier: Programming Language :: Python :: 3
Classifier: Programming Language :: Python :: 3.3
Classifier: Programming Language :: Python :: 3.4
Classifier: Topic :: Office/Business :: Office Suites
Classifier: Topic :: Software Development :: Libraries
Requires-Dist: pandas
Requires-Dist: python-docx
Requires-Dist: uuid
